LICENSE.txt
MANIFEST.in
README.rst
setup.py
raptorizemw/__init__.py
raptorizemw/middleware.py
raptorizemw/resources.py
raptorizemw.egg-info/PKG-INFO
raptorizemw.egg-info/SOURCES.txt
raptorizemw.egg-info/dependency_links.txt
raptorizemw.egg-info/entry_points.txt
raptorizemw.egg-info/not-zip-safe
raptorizemw.egg-info/requires.txt
raptorizemw.egg-info/top_level.txt
raptorizemw/resources/jquery.raptorize.1.0.js
raptorizemw/resources/js_helper.js
raptorizemw/resources/raptor-psd.psd
raptorizemw/resources/raptor-sound.mp3
raptorizemw/resources/raptor-sound.ogg
raptorizemw/resources/raptor.png