Metadata-Version: 1.1
Name: raptorizemw
Version: 0.2.0
Summary: Every WSGI app is better with a raptor.
Home-page: http://github.com/ralphbean/raptorizemw
Author: Ralph Bean
Author-email: ralph.bean@gmail.com
License: MIT
Keywords: raptor raptorize hilarity
Platform: UNKNOWN
Classifier: Development Status :: 4 - Beta
Classifier: Topic :: Internet :: WWW/HTTP :: WSGI :: Middleware
Classifier: Intended Audience :: Developers
Classifier: License :: OSI Approved :: MIT License
